cricbuzzpy/__init__.py
cricbuzzpy/player.py
cricbuzz_stats-0.0.2.dist-info/LICENSE
cricbuzz_stats-0.0.2.dist-info/METADATA
cricbuzz_stats-0.0.2.dist-info/WHEEL
cricbuzz_stats-0.0.2.dist-info/top_level.txt
cricbuzz_stats-0.0.2.dist-info/RECORD
