Metadata-Version: 2.1
Name: cricbuzz-stats
Version: 0.0.2
Summary: A pythonic interface to Cricbuzz that extracts Player stats
Home-page: https://github.com/shiv6146/cricbuzzpy
Author: Shiva Shankar
Author-email: siv6146@gmail.com
Classifier: Programming Language :: Python :: 3
Classifier: License :: OSI Approved :: Apache Software License
Classifier: Operating System :: OS Independent
Requires-Python: >=3.7
License-File: LICENSE
